gum/__init__.py
gum/batcher.py
gum/cli.py
gum/db_utils.py
gum/gum.py
gum/models.py
gum/schemas.py
gum/observers/__init__.py
gum/observers/observer.py
gum/observers/screen.py
gum/prompts/__init__.py
gum/prompts/gum.py
gum/prompts/screen.py
gum_ai-0.1.11.dist-info/licenses/LICENSE
gum_ai-0.1.11.dist-info/METADATA
gum_ai-0.1.11.dist-info/WHEEL
gum_ai-0.1.11.dist-info/entry_points.txt
gum_ai-0.1.11.dist-info/top_level.txt
gum_ai-0.1.11.dist-info/RECORD
