Metadata-Version: 2.4
Name: gum-ai
Version: 0.1.11
Home-page: https://github.com/GeneralUserModels/gum
Author: Omar Shaikh
Author-email: Omar Shaikh <oshaikh13@gmail.com>
License: MIT
Project-URL: Homepage, https://github.com/GeneralUserModels/gum
Requires-Python: >=3.6
License-File: LICENSE
Requires-Dist: pillow
Requires-Dist: mss
Requires-Dist: pynput
Requires-Dist: shapely
Requires-Dist: pyobjc-framework-Quartz
Requires-Dist: openai>=1.0.0
Requires-Dist: SQLAlchemy>=2.0.0
Requires-Dist: pydantic>=2.0.0
Requires-Dist: sqlalchemy-utils>=0.41.0
Requires-Dist: python-dotenv>=1.0.0
Requires-Dist: scikit-learn
Requires-Dist: aiosqlite
Requires-Dist: greenlet
Requires-Dist: persist-queue
Requires-Dist: mkdocs>=1.5.0
Requires-Dist: mkdocs-material>=9.0.0
Requires-Dist: mkdocstrings>=0.24.0
Requires-Dist: mkdocstrings-python>=1.7.0
Dynamic: author
Dynamic: home-page
Dynamic: license-file
Dynamic: requires-python
